synapse_protocol/__init__.py
synapse_protocol/app.py
synapse_protocol/protocol.py
synapse_protocol/agents/agent_manager.py
synapse_protocol/agents/crew_manager.py
synapse_protocol/api/routes.py
synapse_protocol/payments/__init__.py
synapse_protocol/payments/core.py
synapse_protocol/payments/exceptions.py
synapse_protocol/payments/models.py
synapse_protocol/payments/xrp_bridge.py
synapse_protocol/websocket/__init__.py
synapse_protocol/websocket/handler.py
synapse_protocol/websocket/manager.py
synapse_protocol-0.1.0.dist-info/licenses/LICENSE
synapse_protocol-0.1.0.dist-info/METADATA
synapse_protocol-0.1.0.dist-info/WHEEL
synapse_protocol-0.1.0.dist-info/top_level.txt
synapse_protocol-0.1.0.dist-info/RECORD
