Metadata-Version: 2.4
Name: synapse-protocol
Version: 0.1.0
Summary: A2A payment protocol with XRP integration and multi-agent system
Author: Synapse Protocol Team
License: MIT
Project-URL: Homepage, https://github.com/synapseprotocol/synapse-protocol
Project-URL: Bug Tracker, https://github.com/synapseprotocol/synapse-protocol/issues
Project-URL: Documentation, https://synapseprotocol.com/docs
Classifier: Development Status :: 3 - Alpha
Classifier: Intended Audience :: Developers
Classifier: License :: OSI Approved :: MIT License
Classifier: Programming Language :: Python :: 3
Classifier: Programming Language :: Python :: 3.8
Classifier: Programming Language :: Python :: 3.9
Classifier: Programming Language :: Python :: 3.10
Classifier: Programming Language :: Python :: 3.11
Requires-Python: >=3.8
License-File: LICENSE
Requires-Dist: flask>=2.0.0
Requires-Dist: flask-cors>=4.0.0
Requires-Dist: flask-socketio>=5.0.0
Requires-Dist: python-socketio>=5.0.0
Requires-Dist: python-engineio>=4.0.0
Requires-Dist: simple-websocket>=0.10.0
Requires-Dist: requests>=2.28.0
Requires-Dist: python-dotenv>=0.19.0
Requires-Dist: crewai>=0.1.0
Requires-Dist: openai>=1.0.0
Requires-Dist: langchain-openai>=0.0.0
Requires-Dist: langchain>=0.1.0
Requires-Dist: langchain-core>=0.1.0
Requires-Dist: gunicorn>=21.0.0
Requires-Dist: eventlet>=0.33.0
Requires-Dist: websockets>=10.0
Provides-Extra: dev
Requires-Dist: pytest>=7.0.0; extra == "dev"
Requires-Dist: black>=22.0.0; extra == "dev"
Requires-Dist: isort>=5.0.0; extra == "dev"
Requires-Dist: flake8>=4.0.0; extra == "dev"
Requires-Dist: mypy>=0.900; extra == "dev"
Dynamic: license-file
